AUTHORS.rst
CONTRIBUTING.rst
HISTORY.rst
LICENSE
MANIFEST.in
README.rst
setup.cfg
setup.py
parrot_integrations/.DS_Store
parrot_integrations/open_ai/__init__.py
parrot_integrations/open_ai/assistants/__init__.py
parrot_integrations/open_ai/assistants/create_assistant.py
parrot_integrations/open_ai/assistants/delete_assistant.py
parrot_integrations/open_ai/assistants/get_assistant.py
parrot_integrations/open_ai/assistants/list_assistants.py
parrot_integrations/open_ai/assistants/update_assistant.py
parrot_integrations/open_ai/files/__init__.py
parrot_integrations/open_ai/files/delete_file.py
parrot_integrations/open_ai/files/get_file.py
parrot_integrations/open_ai/files/list_files.py
parrot_integrations/open_ai/files/upload_file.py
parrot_integrations/open_ai/messages/__init__.py
parrot_integrations/open_ai/messages/create_message.py
parrot_integrations/open_ai/messages/get_message.py
parrot_integrations/open_ai/messages/list_messages.py
parrot_integrations/open_ai/runs/__init__.py
parrot_integrations/open_ai/runs/create_run.py
parrot_integrations/open_ai/runs/get_run.py
parrot_integrations/open_ai/runs/list_runs.py
parrot_integrations/open_ai/threads/__init__.py
parrot_integrations/open_ai/threads/create_thread.py
parrot_integrations/open_ai/threads/delete_thread.py
parrot_integrations/open_ai/threads/get_thread.py
parrot_integrations_ai.egg-info/PKG-INFO
parrot_integrations_ai.egg-info/SOURCES.txt
parrot_integrations_ai.egg-info/dependency_links.txt
parrot_integrations_ai.egg-info/not-zip-safe
parrot_integrations_ai.egg-info/requires.txt
parrot_integrations_ai.egg-info/top_level.txt
tests/__init__.py
tests/conftest.py
tests/test_open_ai.py
tests/mocks/upload.json