Metadata-Version: 2.1
Name: parrot-integrations-ai
Version: 0.0.3
Summary: Python Integration AI
Home-page: https://github.com/perrystallings/parrot-integrations-ai
Author: Perry Stallings
Author-email: astal01@gmail.com
License: MIT license
Keywords: parrot_integrations
Classifier: Development Status :: 2 - Pre-Alpha
Classifier: Intended Audience :: Developers
Classifier: License :: OSI Approved :: MIT License
Classifier: Natural Language :: English
Classifier: Programming Language :: Python :: 3
Classifier: Programming Language :: Python :: 3.6
Classifier: Programming Language :: Python :: 3.7
Classifier: Programming Language :: Python :: 3.8
Requires-Python: >=3.6
License-File: LICENSE
License-File: AUTHORS.rst
Requires-Dist: parrot-integrations-core>=0.0.18
Requires-Dist: openai
Requires-Dist: requests
